{"17obFaJhEbmKGN658o+7ag==":"img-6037-2800x1866.jpg","4wCETzXtnYGBuppUNJmGuw==":"scan0018-1488x1056.jpg","011twT58NpxlB+eeA1Njgg==":"dsc01275-3872x2592.jpg","jdVXPT5Xzx+Ae1eIhodOFA==":"dsc01381-1999x1338.jpg","VrW/zCvQJWU8h9VNTturXg==":"kaas1%20copy-1211x1810.jpg","ftrinz7kvbhOkeacQ+2C2A==":"dsc01360-3872x2592.jpg","JmTHUbTQANztZ3kum+K9Ig==":"kaas2%20copy-2000x1338.jpg","kPG/JrApGPBNzFgIohAm0Q==":"kaas3%20copy-2000x1339.jpg","0EWnnrm9V73s9NecNkKVMQ==":"kaas4%20copy-2000x1339.jpg","HO5WpVhH1A/rlvpkUn2BaQ==":"kaas5%20copy-2000x1338.jpg","ALfBHJ9SLqttc/03JCwsOA==":"kaas6%20copy-1999x1339.jpg","qn0XWmSeSaavolGUQ45lwQ==":"kaas7%20copy-2000x1338.jpg","t3m0GstHMAX5XOYtyx8yEA==":"kaas8%20copy-2000x1338.jpg","AL6pw+0Hy0t2gHZwpCA9WQ==":"kaas9%20copy-2000x1339.jpg","vd+/DOZFSfE2+0jcuAYKJw==":"kaas10%20copy-2000x1338.jpg","ZdUj6F1NcdGcUVU2bhNwlA==":"kaas12%20copy-1201x1795.jpg","OMEtmeBjZVxe8L4SZdFu4g==":"kaasvoorkant-1999x1338.jpg","+vtR+xl1qbJHd204Fj6k7w==":"kaas11%20copy-2000x1338.jpg","eA5xgfhg698jWZRRiBrr5g==":"kaasachterkant-2000x1338.jpg","A9Uf9lGuNiTUrKPjLX+Nww==":"kaas2-2000x1338.jpg","qtBBZNQeA/+I3i5jjxvkMg==":"plaat4-2628x1982.jpg","L3LshLI4Ls2CK/pyzYPovQ==":"plaat1-3125x2092.jpg","eTDybpOlIEM0qCSvN0rozg==":"plaat5-3322x2224.jpg","Zc1wF0lNgaWbEJh3O2qG9w==":"parijs1-2000x1338.jpg","s9YT0RpikOLVN0IVa1T91g==":"parijs2-2000x1338.jpg","959QY7P6eJZp5Oo/ub5PHQ==":"parijs3-2000x1338.jpg","pWuuS5m2heK0gkLGRlmoRw==":"parijs4-2000x1338.jpg","UFnq+SSTz+J6bpK2o5QrsA==":"parijs5-2000x1338.jpg","skYFdN0q7r62K02bdKbrlw==":"parijs6-2000x1339.jpg","t1O++iC1jPiRW9fEhYjVQw==":"parijs7-2000x1339.jpg","tWi0D9uUY7WhFD1gZwUPQA==":"parijs8-2000x1339.jpg","Fns0LzbseKENhA62IUu5Rg==":"parijs9-2000x1338.jpg","tleN6+EetFb4THZG2+pIJQ==":"parijs10-2000x1338.jpg","BjDJaU4/XlXRqNE5j94hlw==":"parijs11-2000x1338.jpg","u0H52FqtcMA5Ae8TmNIHgg==":"parijs12-1999x1337.jpg","BoM29z0mdbHnyY6aZtecQw==":"cover-2000x1339.jpg","AQlQikE3xvvmP+CH3oikZw==":"kaas1-copy-1211x1810.jpg","usDqRX6E0rZE2odxgM+pRA==":"kaasvoorkanta-1999x1338.jpg","Yy/ELcuPfq4HKVb65dUcvQ==":"kaas4-copy-2000x1339.jpg","WTGpMm1aulRcONpzm/D0Eg==":"kaas3-copy-2000x1339.jpg"}